imputeman/__init__.py
imputeman/impute_engine.py
imputeman/imputeman copy.py
imputeman/imputeman.py
imputeman/models.py
imputeman/myllmservice.py
imputeman/prompts.py
imputeman/utils.py
imputeman/core/__init__.py
imputeman/core/config.py
imputeman/core/entities.py
imputeman/flows/__init__.py
imputeman/flows/main_flow.py
imputeman/flows/main_flow_old.py
imputeman/flows/streaming_flow.py
imputeman/services/__init__.py
imputeman/services/extractor_service multiple_product_issue.py
imputeman/services/extractor_service.py
imputeman/services/scraper_service copy.py
imputeman/services/scraper_service.py
imputeman/services/serp_service.py
imputeman/smoke_tests/__init__.py
imputeman/smoke_tests/__main__.py
imputeman/smoke_tests/test_0_serp_without_service.py
imputeman/smoke_tests/test_10_streaming_pipeline_debug.py
imputeman/smoke_tests/test_1_serp_service.py
imputeman/smoke_tests/test_2_scrape_without_service.py
imputeman/smoke_tests/test_3_entities_and_schema.py
imputeman/smoke_tests/test_3_scrape_service.py
imputeman/smoke_tests/test_4_extracthero_without_service.py
imputeman/smoke_tests/test_4_individual_services.py
imputeman/smoke_tests/test_5_extracthero_service.py
imputeman/smoke_tests/test_6_configuration_system.py
imputeman/smoke_tests/test_7_all_services_sequential_manner.py
imputeman/smoke_tests/test_8_integration_basic.py
imputeman/smoke_tests/test_9_all_services_cross_module_parallelization.py
imputeman/smoke_tests/test_x_prefect_integration.py
imputeman/tasks/__init__.py
imputeman/tasks/extract_tasks.py
imputeman/tasks/scrape_tasks.py
imputeman/tasks/serp_tasks.py
imputeman/utils/__init__.py
imputeman/utils/scrape_and_save.py
imputeman-0.0.1.dist-info/METADATA
imputeman-0.0.1.dist-info/WHEEL
imputeman-0.0.1.dist-info/top_level.txt
imputeman-0.0.1.dist-info/RECORD
