Metadata-Version: 2.4
Name: imputeman
Version: 0.0.1
Summary: Prod level data imputation pipeline which encapsulates: >search >scrape >extract >gather >impute
Author: Enes Kuzucu
Classifier: Development Status :: 3 - Alpha
Classifier: Intended Audience :: Developers
Classifier: License :: OSI Approved :: MIT License
Classifier: Programming Language :: Python :: 3
Classifier: Programming Language :: Python :: 3.7
Classifier: Programming Language :: Python :: 3.8
Classifier: Programming Language :: Python :: 3.9
Classifier: Programming Language :: Python :: 3.10
Classifier: Operating System :: OS Independent
Requires-Python: >=3.7
Requires-Dist: python-dotenv
Requires-Dist: serpengine
Requires-Dist: brightdata
Requires-Dist: extracthero
Dynamic: author
Dynamic: classifier
Dynamic: description
Dynamic: description-content-type
Dynamic: requires-dist
Dynamic: requires-python
Dynamic: summary
